[
    {
        "simulation_id": 1,
        "simulation_distribution": "uniform",
        "ToD": "273, 423, 455, 482, 489, 460, 402, 394, 511, 483, 532, 570, 586, 464, 479, 500, 436, 376, 366, 406, 422, 481, 544, 457, 480, 400, 355, 472, 493, 501, 468, 399, 512, 518, 520, 591, 598, 512, 510, 503, 439, 362, 324, 390, 389, 458, 501, 409",
        "car_batch_size": 24,
        "num_of_parking_lots": 50,
        "num_of_cars": "90, 57, 51, 97, 67, 65, 64, 58, 97, 56, 93, 97, 84, 55, 87, 77, 52, 51, 55, 63, 64, 82, 88, 51",
        "min_people": 1,
        "max_people": 5,
        "mean": 75,
        "deviation": 25,
        "scale": 75
    },
    {
        "simulation_id": 2,
        "simulation_distribution": "uniform",
        "ToD": "285, 533, 552, 485, 489, 563, 519, 482, 566, 575, 487, 552, 462, 495, 498, 477, 519, 511, 539, 450, 390, 410, 481, 562, 597, 600, 562, 526, 483, 547, 498, 495, 562, 543, 489, 521, 489, 545, 475, 474, 490, 529, 546, 444, 388, 428, 484, 581",
        "car_batch_size": 24,
        "num_of_parking_lots": 50,
        "num_of_cars": "95, 97, 72, 64, 78, 95, 69, 73, 99, 85, 68, 91, 65, 83, 67, 70, 94, 84, 82, 56, 53, 72, 76, 95",
        "min_people": 1,
        "max_people": 5,
        "mean": 75,
        "deviation": 25,
        "scale": 75
    },
    {
        "simulation_id": 3,
        "simulation_distribution": "uniform",
        "ToD": "233, 356, 548, 601, 578, 541, 419, 426, 526, 575, 593, 553, 443, 458, 449, 408, 485, 593, 507, 534, 601, 662, 511, 488, 495, 453, 500, 556, 583, 555, 413, 481, 558, 552, 539, 562, 486, 473, 446, 419, 512, 606, 519, 531, 564, 594, 484, 438",
        "car_batch_size": 24,
        "num_of_parking_lots": 50,
        "num_of_cars": "82, 53, 98, 99, 77, 81, 52, 82, 96, 88, 85, 80, 52, 88, 60, 52, 93, 95, 57, 88, 94, 89, 55, 84",
        "min_people": 1,
        "max_people": 5,
        "mean": 75,
        "deviation": 25,
        "scale": 75
    },
    {
        "simulation_id": 4,
        "simulation_distribution": "uniform",
        "ToD": "263, 469, 466, 521, 569, 504, 504, 509, 553, 579, 486, 403, 429, 472, 503, 471, 429, 382, 449, 450, 510, 520, 515, 491, 476, 533, 457, 438, 533, 518, 522, 509, 559, 608, 491, 399, 415, 474, 500, 471, 387, 423, 460, 463, 520, 451, 491, 438",
        "car_batch_size": 24,
        "num_of_parking_lots": 50,
        "num_of_cars": "88, 84, 55, 84, 86, 64, 89, 79, 91, 90, 60, 52, 67, 82, 80, 64, 52, 67, 73, 57, 87, 66, 70, 71",
        "min_people": 1,
        "max_people": 5,
        "mean": 75,
        "deviation": 25,
        "scale": 75
    },
    {
        "simulation_id": 5,
        "simulation_distribution": "uniform",
        "ToD": "168, 325, 387, 349, 514, 573, 572, 485, 444, 418, 420, 509, 554, 545, 576, 568, 650, 513, 488, 487, 524, 491, 497, 521, 454, 398, 339, 388, 513, 534, 540, 486, 527, 482, 433, 473, 555, 557, 644, 597, 588, 485, 507, 521, 531, 515, 541, 486",
        "car_batch_size": 24,
        "num_of_parking_lots": 50,
        "num_of_cars": "60, 62, 50, 70, 99, 86, 80, 72, 79, 65, 63, 99, 77, 85, 99, 91, 98, 61, 82, 80, 74, 72, 78, 73",
        "min_people": 1,
        "max_people": 5,
        "mean": 75,
        "deviation": 25,
        "scale": 75
    },
    {
        "simulation_id": 6,
        "simulation_distribution": "uniform",
        "ToD": "264, 406, 440, 386, 494, 465, 454, 454, 483, 404, 498, 516, 504, 422, 435, 553, 487, 436, 499, 573, 562, 475, 530, 505, 553, 528, 427, 425, 481, 484, 449, 468, 484, 446, 479, 470, 467, 408, 518, 615, 505, 454, 465, 551, 580, 471, 498, 485",
        "car_batch_size": 24,
        "num_of_parking_lots": 50,
        "num_of_cars": "89, 67, 58, 61, 98, 61, 55, 77, 74, 53, 89, 72, 61, 62, 82, 100, 56, 67, 88, 85, 78, 54, 94, 68",
        "min_people": 1,
        "max_people": 5,
        "mean": 75,
        "deviation": 25,
        "scale": 75
    },
    {
        "simulation_id": 7,
        "simulation_distribution": "uniform",
        "ToD": "218, 366, 508, 591, 529, 458, 550, 607, 595, 560, 629, 603, 520, 446, 498, 568, 609, 613, 482, 468, 548, 582, 474, 402, 397, 464, 464, 574, 463, 444, 533, 617, 602, 527, 578, 555, 502, 453, 509, 589, 650, 618, 510, 427, 518, 580, 507, 420",
        "car_batch_size": 24,
        "num_of_parking_lots": 50,
        "num_of_cars": "67, 80, 79, 93, 66, 67, 97, 89, 86, 72, 100, 85, 71, 63, 95, 88, 98, 99, 56, 57, 98, 100, 54, 64",
        "min_people": 1,
        "max_people": 5,
        "mean": 75,
        "deviation": 25,
        "scale": 75
    },
    {
        "simulation_id": 8,
        "simulation_distribution": "uniform",
        "ToD": "254, 501, 614, 557, 481, 398, 439, 469, 553, 542, 477, 527, 528, 527, 483, 480, 477, 425, 434, 423, 517, 577, 490, 435, 448, 533, 650, 638, 551, 459, 422, 466, 567, 584, 483, 493, 519, 581, 489, 480, 419, 423, 455, 402, 486, 565, 505, 414",
        "car_batch_size": 24,
        "num_of_parking_lots": 50,
        "num_of_cars": "79, 96, 94, 73, 67, 56, 73, 79, 89, 77, 57, 92, 66, 98, 59, 85, 61, 64, 67, 58, 94, 85, 60, 53",
        "min_people": 1,
        "max_people": 5,
        "mean": 75,
        "deviation": 25,
        "scale": 75
    },
    {
        "simulation_id": 9,
        "simulation_distribution": "uniform",
        "ToD": "294, 495, 618, 553, 505, 533, 592, 563, 458, 498, 458, 499, 448, 445, 457, 456, 453, 426, 541, 524, 612, 570, 574, 457, 567, 585, 627, 560, 575, 538, 578, 511, 460, 511, 490, 503, 445, 412, 467, 403, 427, 453, 541, 570, 621, 532, 532, 487",
        "car_batch_size": 24,
        "num_of_parking_lots": 50,
        "num_of_cars": "100, 93, 99, 83, 82, 75, 96, 63, 61, 96, 56, 74, 60, 63, 87, 58, 76, 72, 91, 81, 99, 61, 98, 66",
        "min_people": 1,
        "max_people": 5,
        "mean": 75,
        "deviation": 25,
        "scale": 75
    },
    {
        "simulation_id": 10,
        "simulation_distribution": "uniform",
        "ToD": "293, 416, 466, 400, 386, 401, 445, 385, 410, 517, 606, 609, 484, 531, 550, 596, 601, 530, 496, 456, 401, 475, 429, 438, 539, 514, 486, 318, 307, 404, 450, 427, 412, 488, 595, 565, 446, 475, 553, 579, 632, 567, 538, 438, 399, 450, 423, 421",
        "car_batch_size": 24,
        "num_of_parking_lots": 50,
        "num_of_cars": "92, 50, 62, 54, 51, 76, 61, 55, 64, 94, 94, 90, 53, 86, 88, 90, 100, 76, 75, 60, 60, 87, 50, 76",
        "min_people": 1,
        "max_people": 5,
        "mean": 75,
        "deviation": 25,
        "scale": 75
    },
    {
        "simulation_id": 11,
        "simulation_distribution": "uniform",
        "ToD": "276, 427, 503, 423, 468, 529, 459, 435, 408, 375, 378, 479, 531, 588, 594, 508, 526, 452, 490, 506, 548, 571, 487, 387, 480, 495, 551, 438, 460, 483, 419, 418, 368, 338, 362, 460, 536, 542, 601, 541, 519, 450, 466, 481, 557, 599, 500, 391",
        "car_batch_size": 24,
        "num_of_parking_lots": 50,
        "num_of_cars": "89, 68, 81, 53, 74, 78, 50, 72, 50, 50, 74, 85, 75, 94, 98, 61, 78, 64, 81, 71, 93, 93, 58, 50",
        "min_people": 1,
        "max_people": 5,
        "mean": 75,
        "deviation": 25,
        "scale": 75
    },
    {
        "simulation_id": 12,
        "simulation_distribution": "uniform",
        "ToD": "150, 365, 402, 466, 533, 522, 445, 409, 383, 351, 502, 596, 588, 525, 578, 563, 570, 483, 530, 588, 561, 549, 535, 508, 399, 416, 454, 533, 543, 504, 471, 464, 415, 392, 477, 567, 557, 516, 590, 587, 565, 485, 530, 542, 550, 556, 515, 479",
        "car_batch_size": 24,
        "num_of_parking_lots": 50,
        "num_of_cars": "52, 87, 55, 92, 82, 74, 58, 61, 64, 58, 87, 95, 68, 77, 100, 81, 75, 75, 92, 83, 79, 69, 87, 75",
        "min_people": 1,
        "max_people": 5,
        "mean": 75,
        "deviation": 25,
        "scale": 75
    },
    {
        "simulation_id": 13,
        "simulation_distribution": "uniform",
        "ToD": "241, 431, 527, 454, 419, 469, 426, 398, 415, 470, 548, 428, 366, 452, 584, 521, 480, 495, 407, 450, 485, 540, 456, 433, 468, 492, 473, 442, 433, 538, 473, 419, 419, 506, 561, 420, 336, 479, 600, 501, 457, 475, 455, 427, 478, 600, 479, 474",
        "car_batch_size": 24,
        "num_of_parking_lots": 50,
        "num_of_cars": "77, 83, 71, 59, 62, 92, 51, 56, 76, 74, 84, 50, 50, 98, 97, 64, 74, 71, 56, 77, 84, 90, 58, 73",
        "min_people": 1,
        "max_people": 5,
        "mean": 75,
        "deviation": 25,
        "scale": 75
    },
    {
        "simulation_id": 14,
        "simulation_distribution": "uniform",
        "ToD": "273, 421, 506, 492, 529, 598, 562, 442, 484, 435, 409, 385, 472, 447, 533, 603, 493, 481, 396, 408, 454, 574, 507, 584, 569, 509, 504, 484, 506, 576, 608, 503, 506, 444, 410, 391, 459, 405, 484, 538, 473, 450, 451, 458, 475, 569, 532, 495",
        "car_batch_size": 24,
        "num_of_parking_lots": 50,
        "num_of_cars": "92, 71, 80, 70, 84, 100, 82, 57, 96, 57, 51, 64, 81, 54, 96, 86, 60, 69, 67, 61, 75, 100, 65, 94",
        "min_people": 1,
        "max_people": 5,
        "mean": 75,
        "deviation": 25,
        "scale": 75
    },
    {
        "simulation_id": 15,
        "simulation_distribution": "uniform",
        "ToD": "202, 426, 477, 408, 352, 511, 573, 604, 545, 460, 472, 487, 531, 529, 529, 594, 598, 586, 502, 467, 489, 426, 418, 458, 478, 576, 512, 399, 401, 501, 585, 569, 557, 493, 509, 525, 543, 550, 555, 572, 613, 549, 424, 414, 443, 401, 450, 467",
        "car_batch_size": 24,
        "num_of_parking_lots": 50,
        "num_of_cars": "68, 97, 62, 54, 64, 97, 89, 85, 79, 54, 88, 85, 82, 75, 87, 97, 86, 85, 51, 80, 69, 54, 74, 79",
        "min_people": 1,
        "max_people": 5,
        "mean": 75,
        "deviation": 25,
        "scale": 75
    },
    {
        "simulation_id": 16,
        "simulation_distribution": "uniform",
        "ToD": "238, 464, 451, 487, 514, 408, 372, 511, 511, 562, 444, 494, 460, 524, 527, 481, 501, 582, 544, 555, 444, 497, 528, 458, 454, 552, 511, 502, 478, 404, 379, 487, 521, 583, 474, 522, 508, 543, 582, 512, 543, 611, 541, 512, 449, 533, 524, 453",
        "car_batch_size": 24,
        "num_of_parking_lots": 50,
        "num_of_cars": "82, 91, 60, 91, 68, 54, 59, 96, 61, 96, 52, 90, 72, 80, 97, 54, 96, 98, 68, 85, 53, 98, 88, 50",
        "min_people": 1,
        "max_people": 5,
        "mean": 75,
        "deviation": 25,
        "scale": 75
    },
    {
        "simulation_id": 17,
        "simulation_distribution": "uniform",
        "ToD": "293, 386, 425, 409, 478, 482, 529, 425, 464, 407, 463, 524, 460, 481, 480, 520, 505, 474, 447, 477, 478, 439, 432, 449, 563, 522, 448, 462, 516, 469, 494, 422, 468, 435, 424, 491, 462, 464, 486, 488, 447, 449, 498, 507, 504, 419, 413, 404",
        "car_batch_size": 24,
        "num_of_parking_lots": 50,
        "num_of_cars": "96, 56, 64, 81, 87, 58, 91, 52, 81, 56, 75, 89, 54, 82, 75, 74, 67, 65, 71, 69, 76, 55, 69, 63",
        "min_people": 1,
        "max_people": 5,
        "mean": 75,
        "deviation": 25,
        "scale": 75
    },
    {
        "simulation_id": 18,
        "simulation_distribution": "uniform",
        "ToD": "205, 350, 394, 446, 474, 440, 483, 542, 517, 555, 548, 506, 498, 516, 589, 630, 482, 472, 445, 450, 517, 540, 462, 397, 397, 400, 397, 427, 479, 441, 482, 554, 519, 548, 560, 520, 426, 450, 516, 577, 449, 449, 482, 468, 479, 452, 454, 411",
        "car_batch_size": 24,
        "num_of_parking_lots": 50,
        "num_of_cars": "62, 63, 53, 75, 79, 59, 90, 86, 65, 90, 83, 60, 74, 78, 91, 100, 50, 87, 64, 66, 94, 75, 64, 55",
        "min_people": 1,
        "max_people": 5,
        "mean": 75,
        "deviation": 25,
        "scale": 75
    },
    {
        "simulation_id": 19,
        "simulation_distribution": "uniform",
        "ToD": "175, 461, 535, 530, 549, 522, 473, 533, 593, 532, 472, 495, 506, 446, 479, 481, 545, 551, 437, 478, 578, 548, 516, 597, 502, 560, 550, 561, 573, 511, 486, 515, 592, 515, 521, 512, 507, 474, 550, 515, 524, 490, 433, 481, 563, 557, 556, 570",
        "car_batch_size": 24,
        "num_of_parking_lots": 50,
        "num_of_cars": "57, 98, 82, 88, 91, 66, 69, 93, 99, 54, 92, 75, 71, 69, 97, 70, 89, 80, 50, 89, 91, 74, 81, 94",
        "min_people": 1,
        "max_people": 5,
        "mean": 75,
        "deviation": 25,
        "scale": 75
    },
    {
        "simulation_id": 20,
        "simulation_distribution": "uniform",
        "ToD": "235, 456, 551, 584, 526, 556, 446, 494, 528, 591, 480, 468, 566, 578, 559, 563, 476, 513, 563, 584, 592, 528, 518, 511, 483, 502, 484, 548, 515, 557, 470, 529, 509, 559, 505, 417, 552, 578, 587, 523, 466, 497, 511, 556, 617, 581, 521, 513",
        "car_batch_size": 24,
        "num_of_parking_lots": 50,
        "num_of_cars": "79, 91, 80, 97, 59, 93, 58, 96, 70, 88, 62, 77, 100, 81, 86, 69, 59, 92, 77, 98, 100, 77, 68, 89",
        "min_people": 1,
        "max_people": 5,
        "mean": 75,
        "deviation": 25,
        "scale": 75
    }
]